byte/__init__.py
byte/executors/__init__.py
byte/executors/pysqlite/__init__.py
byte/executors/pysqlite/main.py
byte/executors/pysqlite/tasks.py
byte/executors/pysqlite/models/__init__.py
byte/executors/pysqlite/models/connection.py
byte/executors/pysqlite/models/cursor.py
byte/executors/pysqlite/models/transaction.py
byte_pysqlite-0.3.0.dist-info/DESCRIPTION.rst
byte_pysqlite-0.3.0.dist-info/METADATA
byte_pysqlite-0.3.0.dist-info/RECORD
byte_pysqlite-0.3.0.dist-info/WHEEL
byte_pysqlite-0.3.0.dist-info/metadata.json
byte_pysqlite-0.3.0.dist-info/pbr.json
byte_pysqlite-0.3.0.dist-info/top_level.txt
