Metadata-Version: 2.0
Name: byte-pysqlite
Version: 0.3.0
Summary: PySQLite executor for byte
Home-page: https://github.com/fuzeman/byte-pysqlite
Author: Dean Gardiner
Author-email: me@dgardiner.net
License: MIT
Platform: UNKNOWN
Classifier: Development Status :: 3 - Alpha
Classifier: Intended Audience :: Developers
Classifier: License :: OSI Approved :: MIT License
Classifier: Operating System :: OS Independent
Classifier: Programming Language :: Python
Classifier: Programming Language :: Python :: 2
Classifier: Programming Language :: Python :: 2 :: Only
Classifier: Programming Language :: Python :: 2.7
Classifier: Programming Language :: Python :: Implementation :: CPython
Classifier: Topic :: Software Development :: Libraries
Requires-Dist: byte (>=0.3.0,<1.0.0)
Requires-Dist: byte-sqlite (>=0.3.0,<1.0.0)
Requires-Dist: pysqlite (>=2.8.0,<3.0.0)
